pypolarisP4/CAPIcommon.dll
pypolarisP4/__init__.py
pypolarisP4/_pypolarisP4.pyd
pypolarisP4-0.0.5.dist-info/LICENSE
pypolarisP4-0.0.5.dist-info/METADATA
pypolarisP4-0.0.5.dist-info/WHEEL
pypolarisP4-0.0.5.dist-info/top_level.txt
pypolarisP4-0.0.5.dist-info/RECORD
