Metadata-Version: 2.1
Name: pypolarisP4
Version: 0.0.5
Summary: pypolarisP4 c++ wrapper for python 3
Home-page: UNKNOWN
Author: Renan Matsuda
Author-email: renan_hiroshi@hotmail.com
License: UNKNOWN
Platform: UNKNOWN
Classifier: Programming Language :: Python :: 3
Classifier: License :: OSI Approved :: MIT License
Classifier: Operating System :: Microsoft :: Windows
